pyzy3d
