Metadata-Version: 1.0
Name: pyzy3d
Version: 1.0.1rc2
Summary: 3d charts for Python
Home-page: https://github.com/jzy3d/pyzy3d
Author: Martin Pernollet
Author-email: martin@jzy3d.org
License: MIT
Platform: UNKNOWN
